Workbook

Sheet 📋 Инструкция
B1: MedВычет — Калькулятор расходов
B2: Версия: 2.0 · Март 2025 · Расчёт в рублях с НДС
B4: ЛИСТЫ В ФАЙЛЕ
B5: 📋 Инструкция | C5: Легенда и описание модели
B6: ⚙️ Допущения | C6: Все изменяемые параметры (синий цвет = ввод)
B7: 🚀 MVP (0–100 MAU) | C7: Расходы на период разработки и начального запуска
B8: 📈 1 000 MAU | C8: Расходы при 1 000 активных пользователей в месяц
B9: 🚀 5 000 MAU | C9: Расходы при 5 000 активных пользователей в месяц
B10: 📊 Сводка | C10: Итоговое сравнение всех сценариев на одном листе
B12: ЦВЕТОВАЯ ЛЕГЕНДА
B13: Синий текст | C13: Изменяемое допущение / входной параметр (вводи здесь)
B14: Чёрный текст | C14: Формула / расчётное значение (не менять вручную)
B15: Жёлтый фон | C15: Ключевое допущение — требует особого внимания
B17: ИСТОЧНИКИ ЦЕН
B18: Yandex Cloud | C18: yandex.cloud/ru/prices — цены актуальны на март 2025 (повышение до 8% с 1 мая 2025)
B19: YOS (Object Storage) | C19: 100 ГБ = 68 ₽/мес (холодное хранилище)
B20: Google Vision API | C20: $1.50 / 1000 запросов OCR, первые 1000 — бесплатно
B21: Sentry | C21: Developer (бесплатно до 5k ошибок/мес), Team от 2160 ₽/мес
B22: Курс USD→RUB | C22: Допущение: 90 ₽/$. Изменить в листе Допущения

Sheet ⚙️ Допущения
B1: ⚙️ Допущения — все изменяемые параметры модели
B2: Параметр | C2: MVP (0–100 MAU) | D2: 1 000 MAU | E2: 5 000 MAU | F2: Ед. изм. | G2: Примечание
B3: 👥 Пользователи
B4: MAU (активных пользователей/мес) | C4: 50 | D4: 1000 | E4: 5000 | G4: Изменяемый параметр
B5: Чеков на пользователя/мес (avg) | C5: 5 | D5: 8 | E5: 10 | G5: Free: 20/год → ~2/мес; Pro: без лимита
B6: Доля Pro-пользователей | C6: 0.05 | D6: 0.08 | E6: 0.12 | G6: Целевая конверсия Free → Pro
B7: Цена Pro-тарифа (₽/год) | C7: 499 | D7: 499 | E7: 499 | G7: Текущий прайс
B8: 🧾 Чеки и OCR
B9: Доля чеков с QR-кодом | C9: 0.65 | D9: 0.7 | E9: 0.75 | G9: Аптечные чеки с 2017г. обязаны иметь QR
B10: Доля Pro-чеков → Vision API (Фаза 7) | C10: 0 | D10: 0 | E10: 0.5 | G10: 0% до Фазы 7
B11: Рецептов загружается / чек | C11: 0.6 | D11: 0.7 | E11: 0.7 | G11: Не каждый чек требует рецепта
B12: 💱 Валюта и прочее
B13: Курс USD → RUB | C13: 90 | D13: 90 | E13: 90 | G13: Использовать текущий курс ЦБ
B14: НДС включён в цены (да=1) | C14: 1 | D14: 1 | E14: 1 | G14: Все цены Yandex Cloud с НДС
B15: 🖥️ Виртуальные машины (Yandex Cloud Compute)
B16: API-серверы: кол-во ВМ | C16: 1 | D16: 2 | E16: 3 | G16: 2 vCPU / 4 GB RAM каждая
B17: API-сервер: цена ВМ (₽/мес) | C17: 1800 | D17: 1800 | E17: 1800 | G17: 2vCPU+4GB, standard-v3, RU. Источник: Yandex Cloud
B18: OCR-воркеры: кол-во ВМ | C18: 1 | D18: 2 | E18: 4 | G18: 4 vCPU / 8 GB RAM каждая
B19: OCR-воркер: цена ВМ (₽/мес) | C19: 3200 | D19: 3200 | E19: 3200 | G19: 4vCPU+8GB, standard-v3, RU. Источник: Yandex Cloud
B20: Балансировщик нагрузки (₽/мес) | C20: 0 | D20: 650 | E20: 650 | G20: Yandex Application Load Balancer
B21: 🗄️ База данных (Yandex Managed PostgreSQL)
B22: PostgreSQL кластер (₽/мес) | C22: 2500 | D22: 5500 | E22: 9500 | G22: s3-c2-m8 → s3-c4-m16. Источник: Yandex Cloud от 824 ₽
B23: SSD-диск БД (₽/мес за 10 ГБ) | C23: 100 | D23: 200 | E23: 400 | G23: ~10 ₽/ГБ/мес SSD. Увеличивать по мере роста
B24: ⚡ Redis (очереди Celery)
B25: Redis: цена (₽/мес) | C25: 1200 | D25: 2400 | E25: 4200 | G25: Yandex Managed Redis. hm1.nano → hm1.small
B26: 📦 Yandex Object Storage
B27: Хранилище чеков (ГБ/мес прирост) | C27: 5 | D27: 40 | E27: 180 | G27: ~150 КБ/фото × чеки × MAU
B28: Хранилище рецептов (ГБ/мес прирост) | C28: 3 | D28: 25 | E28: 110 | G28: ~200 КБ/фото × рецепты × MAU
B29: Цена YOS (₽/ГБ/мес) | C29: 0.68 | D29: 0.68 | E29: 0.68 | G29: Стандартное хранилище. Источник: hosting.kitchen/yandex-cloud
B30: Исходящий трафик (ГБ/мес) | C30: 10 | D30: 80 | E30: 350 | G30: pre-signed URL: ~1 МБ на просмотр
B31: Цена трафика YOS (₽/ГБ) | C31: 1.53 | D31: 1.53 | E31: 1.53 | G31: Исходящий трафик Yandex Cloud
B32: 👁️ Google Vision API (Фаза 7, Pro-тариф)
B33: Цена Vision API ($/1000 запросов) | C33: 1.5 | D33: 1.5 | E33: 1.5 | G33: Text Detection OCR. Источник: cloud.google.com/vision/pricing
B34: Бесплатных запросов/мес | C34: 1000 | D34: 1000 | E34: 1000 | G34: Первые 1000 ед./мес бесплатно
B35: 🔧 Сторонние сервисы
B36: Sentry (мониторинг, ₽/мес) | C36: 0 | D36: 0 | E36: 2160 | G36: Developer (бесплатно) → Team от 2160 ₽
B37: Домен + SSL (₽/мес) | C37: 100 | D37: 100 | E37: 100 | G37: ~1200 ₽/год домен + Let's Encrypt (бесплатно)
B38: Резерв / прочее (₽/мес) | C38: 500 | D38: 1000 | E38: 3000 | G38: Email-рассылка, логи, непредвиденное

Sheet 🚀 MVP (0–100 MAU)
B1: MedВычет — MVP (0–100 MAU)
B2: Ежемесячные расходы (₽, с НДС) · Все цены изменяются в листе ⚙️ Допущения
B3: Статья расходов | C3: ₽/мес | D3: ₽/год | E3: Комментарий
B4: 🖥️ Виртуальные машины
B5: API-серверы | C5: ='⚙️ Допущения'!C16*'⚙️ Допущения'!C17 -> 1800 | D5: =C5*12 -> 21600 | E5: кол-во × 1 800 ₽/мес · 2vCPU/4GB
B6: OCR-воркеры (Celery) | C6: ='⚙️ Допущения'!C18*'⚙️ Допущения'!C19 -> 3200 | D6: =C6*12 -> 38400 | E6: кол-во × 3 200 ₽/мес · 4vCPU/8GB
B7: Балансировщик нагрузки | C7: ='⚙️ Допущения'!C20 -> 0 | D7: =C7*12 -> 0 | E7: Yandex ALB. MVP: не нужен
B8: Итого: ВМ | C8: =SUM(C5:C7) -> 5000 | D8: =C8*12 -> 60000
B9: 🗄️ База данных
B10: PostgreSQL кластер (Managed) | C10: ='⚙️ Допущения'!C22 -> 2500 | D10: =C10*12 -> 30000 | E10: Yandex Managed PostgreSQL. MVP: s3-c2-m8
B11: SSD-диск БД | C11: ='⚙️ Допущения'!C23 -> 100 | D11: =C11*12 -> 1200 | E11: ~10 ₽/ГБ/мес SSD
B12: Redis (Celery очереди) | C12: ='⚙️ Допущения'!C25 -> 1200 | D12: =C12*12 -> 14400 | E12: Yandex Managed Redis
B13: Итого: БД + Redis | C13: =SUM(C10:C12) -> 3800 | D13: =C13*12 -> 45600
B14: 📦 Yandex Object Storage
B15: Хранилище чеков | C15: ='⚙️ Допущения'!C27*'⚙️ Допущения'!C29 -> 3.4 | D15: =C15*12 -> 40.8 | E15: ГБ прирост × 0.68 ₽/ГБ
B16: Хранилище рецептов | C16: ='⚙️ Допущения'!C28*'⚙️ Допущения'!C29 -> 2.04 | D16: =C16*12 -> 24.48 | E16: ГБ прирост × 0.68 ₽/ГБ
B17: Исходящий трафик | C17: ='⚙️ Допущения'!C30*'⚙️ Допущения'!C31 -> 15.3 | D17: =C17*12 -> 183.6 | E17: pre-signed URL просмотры
B18: Итого: Object Storage | C18: =SUM(C15:C17) -> 20.74 | D18: =C18*12 -> 248.88
B19: 🔍 OCR — расходы на распознавание
B20: EasyOCR + Tesseract | C20: =0 -> 0 | D20: =C20*12 -> 0 | E20: Бесплатно (open-source, запускается на своих ВМ)
B21: ФНС Open API | C21: =0 -> 0 | D21: =C21*12 -> 0 | E21: Бесплатно (официальный API ФНС)
B22: Google Vision API (Фаза 7, Pro-тариф) | C22: =MAX(0, ('⚙️ Допущения'!C4 * '⚙️ Допущения'!C5 * '⚙️ Допущения'!C10 - '⚙️ Допущения'!C34/1000) * '⚙️ Допущения'!C33 * '⚙️ Допущения'!C13 / 1) -> 0 | D22: =C22*12 -> 0 | E22: MAU × чеков × доля Pro × $1.50/1000 × курс (после 1000 бесплатных)
B23: Итого: OCR | C23: =SUM(C20:C22) -> 0 | D23: =C23*12 -> 0
B24: 🔧 Сторонние сервисы
B25: Sentry (мониторинг ошибок) | C25: ='⚙️ Допущения'!C36 -> 0 | D25: =C25*12 -> 0 | E25: MVP/1k MAU: бесплатно. 5k MAU: Team 2160 ₽/мес
B26: Домен + SSL | C26: ='⚙️ Допущения'!C37 -> 100 | D26: =C26*12 -> 1200 | E26: ~1200 ₽/год домен + Let's Encrypt (бесплатно)
B27: Резерв / прочее | C27: ='⚙️ Допущения'!C38 -> 500 | D27: =C27*12 -> 6000 | E27: Email, логи, непредвиденные расходы
B28: Итого: Сторонние сервисы | C28: =SUM(C25:C27) -> 600 | D28: =C28*12 -> 7200
B30: 💰 ИТОГО РАСХОДОВ В МЕСЯЦ | C30: =C8+C13+C18+C23+C28 -> 9420.74 | D30: =C30*12 -> 113048.88
B31: 💰 ИТОГО РАСХОДОВ В ГОД | C31: =C30*12 -> 113048.88 | D31: =C31*12 -> 1356586.6
B33: 📊 Упрощённый P&L (выручка vs расходы)
B34: MAU | C34: ='⚙️ Допущения'!C4 -> 50 | D34: =C34*12 -> 600 | E34: Из листа Допущения
B35: Доля Pro-пользователей | C35: ='⚙️ Допущения'!C6 -> 0.05 | D35: =C35*12 -> 0.6
B36: Pro-пользователей (чел.) | C36: =ROUND(C34*C35, 0) -> 3 | D36: =C36*12 -> 36 | E36: MAU × доля Pro
B37: Выручка (₽/мес) | C37: =ROUND(C36*'⚙️ Допущения'!C7/12, 0) -> 125 | D37: =C37*12 -> 1500 | E37: Pro-юзеры × 499 ₽/год / 12
B38: Расходы (₽/мес) | C38: =C30 -> 9420.74 | D38: =C38*12 -> 113048.88
B39: EBITDA (₽/мес) | C39: =C37-C38 -> -9295.74 | D39: =C39*12 -> -111548.88 | E39: ⚠️ Не включает з/п команды. Отрицательное значение = субсидируемый рост

Sheet 📈 1 000 MAU
B1: MedВычет — 1 000 MAU
B2: Ежемесячные расходы (₽, с НДС) · Все цены изменяются в листе ⚙️ Допущения
B3: Статья расходов | C3: ₽/мес | D3: ₽/год | E3: Комментарий
B4: 🖥️ Виртуальные машины
B5: API-серверы | C5: ='⚙️ Допущения'!D16*'⚙️ Допущения'!D17 -> 3600 | D5: =C5*12 -> 43200 | E5: кол-во × 1 800 ₽/мес · 2vCPU/4GB
B6: OCR-воркеры (Celery) | C6: ='⚙️ Допущения'!D18*'⚙️ Допущения'!D19 -> 6400 | D6: =C6*12 -> 76800 | E6: кол-во × 3 200 ₽/мес · 4vCPU/8GB
B7: Балансировщик нагрузки | C7: ='⚙️ Допущения'!D20 -> 650 | D7: =C7*12 -> 7800 | E7: Yandex ALB. MVP: не нужен
B8: Итого: ВМ | C8: =SUM(C5:C7) -> 10650 | D8: =C8*12 -> 127800
B9: 🗄️ База данных
B10: PostgreSQL кластер (Managed) | C10: ='⚙️ Допущения'!D22 -> 5500 | D10: =C10*12 -> 66000 | E10: Yandex Managed PostgreSQL. MVP: s3-c2-m8
B11: SSD-диск БД | C11: ='⚙️ Допущения'!D23 -> 200 | D11: =C11*12 -> 2400 | E11: ~10 ₽/ГБ/мес SSD
B12: Redis (Celery очереди) | C12: ='⚙️ Допущения'!D25 -> 2400 | D12: =C12*12 -> 28800 | E12: Yandex Managed Redis
B13: Итого: БД + Redis | C13: =SUM(C10:C12) -> 8100 | D13: =C13*12 -> 97200
B14: 📦 Yandex Object Storage
B15: Хранилище чеков | C15: ='⚙️ Допущения'!D27*'⚙️ Допущения'!D29 -> 27.2 | D15: =C15*12 -> 326.4 | E15: ГБ прирост × 0.68 ₽/ГБ
B16: Хранилище рецептов | C16: ='⚙️ Допущения'!D28*'⚙️ Допущения'!D29 -> 17 | D16: =C16*12 -> 204 | E16: ГБ прирост × 0.68 ₽/ГБ
B17: Исходящий трафик | C17: ='⚙️ Допущения'!D30*'⚙️ Допущения'!D31 -> 122.4 | D17: =C17*12 -> 1468.8 | E17: pre-signed URL просмотры
B18: Итого: Object Storage | C18: =SUM(C15:C17) -> 166.6 | D18: =C18*12 -> 1999.2
B19: 🔍 OCR — расходы на распознавание
B20: EasyOCR + Tesseract | C20: =0 -> 0 | D20: =C20*12 -> 0 | E20: Бесплатно (open-source, запускается на своих ВМ)
B21: ФНС Open API | C21: =0 -> 0 | D21: =C21*12 -> 0 | E21: Бесплатно (официальный API ФНС)
B22: Google Vision API (Фаза 7, Pro-тариф) | C22: =MAX(0, ('⚙️ Допущения'!D4 * '⚙️ Допущения'!D5 * '⚙️ Допущения'!D10 - '⚙️ Допущения'!D34/1000) * '⚙️ Допущения'!D33 * '⚙️ Допущения'!D13 / 1) -> 0 | D22: =C22*12 -> 0 | E22: MAU × чеков × доля Pro × $1.50/1000 × курс (после 1000 бесплатных)
B23: Итого: OCR | C23: =SUM(C20:C22) -> 0 | D23: =C23*12 -> 0
B24: 🔧 Сторонние сервисы
B25: Sentry (мониторинг ошибок) | C25: ='⚙️ Допущения'!D36 -> 0 | D25: =C25*12 -> 0 | E25: MVP/1k MAU: бесплатно. 5k MAU: Team 2160 ₽/мес
B26: Домен + SSL | C26: ='⚙️ Допущения'!D37 -> 100 | D26: =C26*12 -> 1200 | E26: ~1200 ₽/год домен + Let's Encrypt (бесплатно)
B27: Резерв / прочее | C27: ='⚙️ Допущения'!D38 -> 1000 | D27: =C27*12 -> 12000 | E27: Email, логи, непредвиденные расходы
B28: Итого: Сторонние сервисы | C28: =SUM(C25:C27) -> 1100 | D28: =C28*12 -> 13200
B30: 💰 ИТОГО РАСХОДОВ В МЕСЯЦ | C30: =C8+C13+C18+C23+C28 -> 20016.6 | D30: =C30*12 -> 240199.2
B31: 💰 ИТОГО РАСХОДОВ В ГОД | C31: =C30*12 -> 240199.2 | D31: =C31*12 -> 2882390.4
B33: 📊 Упрощённый P&L (выручка vs расходы)
B34: MAU | C34: ='⚙️ Допущения'!D4 -> 1000 | D34: =C34*12 -> 12000 | E34: Из листа Допущения
B35: Доля Pro-пользователей | C35: ='⚙️ Допущения'!D6 -> 0.08 | D35: =C35*12 -> 0.96
B36: Pro-пользователей (чел.) | C36: =ROUND(C34*C35, 0) -> 80 | D36: =C36*12 -> 960 | E36: MAU × доля Pro
B37: Выручка (₽/мес) | C37: =ROUND(C36*'⚙️ Допущения'!D7/12, 0) -> 3327 | D37: =C37*12 -> 39924 | E37: Pro-юзеры × 499 ₽/год / 12
B38: Расходы (₽/мес) | C38: =C30 -> 20016.6 | D38: =C38*12 -> 240199.2
B39: EBITDA (₽/мес) | C39: =C37-C38 -> -16689.6 | D39: =C39*12 -> -200275.2 | E39: ⚠️ Не включает з/п команды. Отрицательное значение = субсидируемый рост

Sheet 🚀 5 000 MAU
B1: MedВычет — 🚀 5 000 MAU
B2: Ежемесячные расходы (₽, с НДС) · Все цены изменяются в листе ⚙️ Допущения
B3: Статья расходов | C3: ₽/мес | D3: ₽/год | E3: Комментарий
B4: 🖥️ Виртуальные машины
B5: API-серверы | C5: ='⚙️ Допущения'!E16*'⚙️ Допущения'!E17 -> 5400 | D5: =C5*12 -> 64800 | E5: кол-во × 1 800 ₽/мес · 2vCPU/4GB
B6: OCR-воркеры (Celery) | C6: ='⚙️ Допущения'!E18*'⚙️ Допущения'!E19 -> 12800 | D6: =C6*12 -> 153600 | E6: кол-во × 3 200 ₽/мес · 4vCPU/8GB
B7: Балансировщик нагрузки | C7: ='⚙️ Допущения'!E20 -> 650 | D7: =C7*12 -> 7800 | E7: Yandex ALB. MVP: не нужен
B8: Итого: ВМ | C8: =SUM(C5:C7) -> 18850 | D8: =C8*12 -> 226200
B9: 🗄️ База данных
B10: PostgreSQL кластер (Managed) | C10: ='⚙️ Допущения'!E22 -> 9500 | D10: =C10*12 -> 114000 | E10: Yandex Managed PostgreSQL. MVP: s3-c2-m8
B11: SSD-диск БД | C11: ='⚙️ Допущения'!E23 -> 400 | D11: =C11*12 -> 4800 | E11: ~10 ₽/ГБ/мес SSD
B12: Redis (Celery очереди) | C12: ='⚙️ Допущения'!E25 -> 4200 | D12: =C12*12 -> 50400 | E12: Yandex Managed Redis
B13: Итого: БД + Redis | C13: =SUM(C10:C12) -> 14100 | D13: =C13*12 -> 169200
B14: 📦 Yandex Object Storage
B15: Хранилище чеков | C15: ='⚙️ Допущения'!E27*'⚙️ Допущения'!E29 -> 122.4 | D15: =C15*12 -> 1468.8 | E15: ГБ прирост × 0.68 ₽/ГБ
B16: Хранилище рецептов | C16: ='⚙️ Допущения'!E28*'⚙️ Допущения'!E29 -> 74.8 | D16: =C16*12 -> 897.6 | E16: ГБ прирост × 0.68 ₽/ГБ
B17: Исходящий трафик | C17: ='⚙️ Допущения'!E30*'⚙️ Допущения'!E31 -> 535.5 | D17: =C17*12 -> 6426 | E17: pre-signed URL просмотры
B18: Итого: Object Storage | C18: =SUM(C15:C17) -> 732.7 | D18: =C18*12 -> 8792.4
B19: 🔍 OCR — расходы на распознавание
B20: EasyOCR + Tesseract | C20: =0 -> 0 | D20: =C20*12 -> 0 | E20: Бесплатно (open-source, запускается на своих ВМ)
B21: ФНС Open API | C21: =0 -> 0 | D21: =C21*12 -> 0 | E21: Бесплатно (официальный API ФНС)
B22: Google Vision API (Фаза 7, Pro-тариф) | C22: =MAX(0, ('⚙️ Допущения'!E4 * '⚙️ Допущения'!E5 * '⚙️ Допущения'!E10 - '⚙️ Допущения'!E34/1000) * '⚙️ Допущения'!E33 * '⚙️ Допущения'!E13 / 1) -> 3374865 | D22: =C22*12 -> 40498380 | E22: MAU × чеков × доля Pro × $1.50/1000 × курс (после 1000 бесплатных)
B23: Итого: OCR | C23: =SUM(C20:C22) -> 3374865 | D23: =C23*12 -> 40498380
B24: 🔧 Сторонние сервисы
B25: Sentry (мониторинг ошибок) | C25: ='⚙️ Допущения'!E36 -> 2160 | D25: =C25*12 -> 25920 | E25: MVP/1k MAU: бесплатно. 5k MAU: Team 2160 ₽/мес
B26: Домен + SSL | C26: ='⚙️ Допущения'!E37 -> 100 | D26: =C26*12 -> 1200 | E26: ~1200 ₽/год домен + Let's Encrypt (бесплатно)
B27: Резерв / прочее | C27: ='⚙️ Допущения'!E38 -> 3000 | D27: =C27*12 -> 36000 | E27: Email, логи, непредвиденные расходы
B28: Итого: Сторонние сервисы | C28: =SUM(C25:C27) -> 5260 | D28: =C28*12 -> 63120
B30: 💰 ИТОГО РАСХОДОВ В МЕСЯЦ | C30: =C8+C13+C18+C23+C28 -> 3413807.7 | D30: =C30*12 -> 40965692
B31: 💰 ИТОГО РАСХОДОВ В ГОД | C31: =C30*12 -> 40965692 | D31: =C31*12 -> 4.9158831e+08
B33: 📊 Упрощённый P&L (выручка vs расходы)
B34: MAU | C34: ='⚙️ Допущения'!E4 -> 5000 | D34: =C34*12 -> 60000 | E34: Из листа Допущения
B35: Доля Pro-пользователей | C35: ='⚙️ Допущения'!E6 -> 0.12 | D35: =C35*12 -> 1.44
B36: Pro-пользователей (чел.) | C36: =ROUND(C34*C35, 0) -> 600 | D36: =C36*12 -> 7200 | E36: MAU × доля Pro
B37: Выручка (₽/мес) | C37: =ROUND(C36*'⚙️ Допущения'!E7/12, 0) -> 24950 | D37: =C37*12 -> 299400 | E37: Pro-юзеры × 499 ₽/год / 12
B38: Расходы (₽/мес) | C38: =C30 -> 3413807.7 | D38: =C38*12 -> 40965692
B39: EBITDA (₽/мес) | C39: =C37-C38 -> -3388857.7 | D39: =C39*12 -> -40666292 | E39: ⚠️ Не включает з/п команды. Отрицательное значение = субсидируемый рост

Sheet 📊 Сводка
B1: 📊 Сводка — сравнение сценариев
B2: Все значения подтягиваются автоматически из листов сценариев
B3: Статья | C3: MVP (0–100 MAU) | D3: 1 000 MAU | E3: 5 000 MAU | F3: Примечание
B4: 🖥️ ВМ (API + OCR воркеры) | C4: ='🚀 MVP (0–100 MAU)'!C8 -> 5000 | D4: ='📈 1 000 MAU'!C8 -> 10650 | E4: ='🚀 5 000 MAU'!C8 -> 18850 | F4: 3 API + 4 OCR воркеры
B5: 🗄️ БД + Redis | C5: ='🚀 MVP (0–100 MAU)'!C13 -> 3800 | D5: ='📈 1 000 MAU'!C13 -> 8100 | E5: ='🚀 5 000 MAU'!C13 -> 14100 | F5: PostgreSQL s3-c4 + Redis medium
B6: 📦 Object Storage | C6: ='🚀 MVP (0–100 MAU)'!C18 -> 20.74 | D6: ='📈 1 000 MAU'!C18 -> 166.6 | E6: ='🚀 5 000 MAU'!C18 -> 732.7 | F6: ~180 ГБ/мес прирост
B7: 🔍 OCR (Vision API) | C7: ='🚀 MVP (0–100 MAU)'!C23 -> 0 | D7: ='📈 1 000 MAU'!C23 -> 0 | E7: ='🚀 5 000 MAU'!C23 -> 3374865 | F7: Vision API для Pro (50%)
B8: 🔧 Сторонние сервисы | C8: ='🚀 MVP (0–100 MAU)'!C28 -> 600 | D8: ='📈 1 000 MAU'!C28 -> 1100 | E8: ='🚀 5 000 MAU'!C28 -> 5260 | F8: Sentry Team + резерв
B9: 💰 ИТОГО ₽/МЕС | C9: ='🚀 MVP (0–100 MAU)'!C30 -> 9420.74 | D9: ='📈 1 000 MAU'!C30 -> 20016.6 | E9: ='🚀 5 000 MAU'!C30 -> 3413807.7
B10: 💰 ИТОГО ₽/ГОД | C10: ='🚀 MVP (0–100 MAU)'!C31 -> 113048.88 | D10: ='📈 1 000 MAU'!C31 -> 240199.2 | E10: ='🚀 5 000 MAU'!C31 -> 40965692
B11: 👥 MAU | C11: ='🚀 MVP (0–100 MAU)'!C34 -> 50 | D11: ='📈 1 000 MAU'!C34 -> 1000 | E11: ='🚀 5 000 MAU'!C34 -> 5000
B12: 💵 Выручка ₽/мес | C12: ='🚀 MVP (0–100 MAU)'!C37 -> 125 | D12: ='📈 1 000 MAU'!C37 -> 3327 | E12: ='🚀 5 000 MAU'!C37 -> 24950 | F12: Конверсия 12%
B13: 📉 EBITDA ₽/мес | C13: ='🚀 MVP (0–100 MAU)'!C39 -> -9295.74 | D13: ='📈 1 000 MAU'!C39 -> -16689.6 | E13: ='🚀 5 000 MAU'!C39 -> -3388857.7 | F13: ~600 Pro-юзеров
